hftc/__init__.py
hftc/cache.py
hftorchcache-0.0.2.dist-info/METADATA
hftorchcache-0.0.2.dist-info/WHEEL
hftorchcache-0.0.2.dist-info/entry_points.txt
hftorchcache-0.0.2.dist-info/licenses/LICENSE
hftorchcache-0.0.2.dist-info/RECORD
