Metadata-Version: 2.1
Name: hftorchcache
Version: 0.0.2
Summary: Efficient caching of Hugging Face models using PyTorch serialisation
Author-Email: Louis Maddox <louismmx@gmail.com>
License: MIT
Project-URL: Homepage, https://github.com/lmmx/hftorchcache
Project-URL: Repository, https://github.com/lmmx/hftorchcache.git
Requires-Python: >=3.10
Requires-Dist: accelerate>=1.3.0
Requires-Dist: platformdirs>=4.3.6
Requires-Dist: torch>=2.0.0
Requires-Dist: transformers>=4.0.0
